seqpro-0.9.0.dist-info/METADATA
seqpro-0.9.0.dist-info/WHEEL
seqpro-0.9.0.dist-info/licenses/LICENSE
seqpro.libs/libgcc_s-98a1ef30.so.1
seqpro/__init__.py
seqpro/_analyzers.py
seqpro/_cleaners.py
seqpro/_encoders.py
seqpro/_modifiers.py
seqpro/_numba.py
seqpro/_types.py
seqpro/_utils.py
seqpro/alphabets/__init__.py
seqpro/alphabets/_alphabets.py
seqpro/bed.py
seqpro/experimental/_experimental.py
seqpro/experimental/_visualizers.py
seqpro/gtf.py
seqpro/py.typed
seqpro/rag/__init__.py
seqpro/rag/_array.py
seqpro/rag/_gufuncs.py
seqpro/rag/_types.py
seqpro/rag/_utils.py
seqpro/seqpro.abi3.so
seqpro/transforms/__init__.py
seqpro/transforms/augmentation.py
seqpro/transforms/tmm.py
seqpro/xr/__init__.py
seqpro-0.9.0.dist-info/RECORD
