Metadata-Version: 2.4
Name: seqpro
Version: 0.9.0
Classifier: Programming Language :: Rust
Classifier: Programming Language :: Python :: Implementation :: CPython
Classifier: Programming Language :: Python :: Implementation :: PyPy
Requires-Dist: numba>=0.58.1
Requires-Dist: numpy>=1.26.0
Requires-Dist: polars>=1.10.0,<2
Requires-Dist: pyranges>=0.1.3,<0.2
Requires-Dist: pandera>=0.22.1
Requires-Dist: pandas
Requires-Dist: pyarrow
Requires-Dist: natsort
Requires-Dist: setuptools>=70
Requires-Dist: awkward>=2.5.0
License-File: LICENSE
Author-email: David Laub <dlaub@ucsd.edu>, Adam Klie <aklie@ucsd.edu>
Requires-Python: >=3.9
